CHANGES.txt
COPYRIGHT.txt
LICENSE.txt
README.txt
bootstrap.py
buildout.cfg
setup.py
src/zamplugin/__init__.py
src/zamplugin.authenticator.egg-info/PKG-INFO
src/zamplugin.authenticator.egg-info/SOURCES.txt
src/zamplugin.authenticator.egg-info/dependency_links.txt
src/zamplugin.authenticator.egg-info/namespace_packages.txt
src/zamplugin.authenticator.egg-info/not-zip-safe
src/zamplugin.authenticator.egg-info/requires.txt
src/zamplugin.authenticator.egg-info/top_level.txt
src/zamplugin/authenticator/README.txt
src/zamplugin/authenticator/__init__.py
src/zamplugin/authenticator/configure.zcml
src/zamplugin/authenticator/ftesting.zcml
src/zamplugin/authenticator/menu.py
src/zamplugin/authenticator/menu.zcml
src/zamplugin/authenticator/plugin.py
src/zamplugin/authenticator/plugin.zcml
src/zamplugin/authenticator/tests.py
src/zamplugin/authenticator/browser/__init__.py
src/zamplugin/authenticator/browser/authenticator.zcml
src/zamplugin/authenticator/browser/configure.zcml
src/zamplugin/authenticator/browser/credential.zcml
src/zamplugin/authenticator/browser/group.zcml
src/zamplugin/authenticator/browser/login.zcml
src/zamplugin/authenticator/browser/user.zcml