Metadata-Version: 1.0
Name: zamplugin.authenticator
Version: 0.6.0
Summary: Site manager support for ZAM (Zope Application Management)
Home-page: http://pypi.python.org/pypi/zamplugin.authenticator
Author: Roger Ineichen and the Zope Community
Author-email: zope-dev@zope.org
License: ZPL 2.1
Keywords: zope zope3 z3c authenticator management user interface
Platform: UNKNOWN
Classifier: Development Status :: 4 - Beta
Classifier: Environment :: Web Environment
Classifier: Intended Audience :: Developers
Classifier: License :: OSI Approved :: Zope Public License
Classifier: Programming Language :: Python
Classifier: Natural Language :: English
Classifier: Operating System :: OS Independent
Classifier: Topic :: Internet :: WWW/HTTP
Classifier: Framework :: Zope3
